triad/__init__.py
triad/constants.py
triad/exceptions.py
triad/py.typed
triad/collections/__init__.py
triad/collections/dict.py
triad/collections/fs.py
triad/collections/function_wrapper.py
triad/collections/schema.py
triad/utils/__init__.py
triad/utils/assertion.py
triad/utils/batch_reslicers.py
triad/utils/class_extension.py
triad/utils/convert.py
triad/utils/dispatcher.py
triad/utils/entry_points.py
triad/utils/hash.py
triad/utils/io.py
triad/utils/iter.py
triad/utils/json.py
triad/utils/pandas_like.py
triad/utils/pyarrow.py
triad/utils/rename.py
triad/utils/schema.py
triad/utils/string.py
triad/utils/threading.py
triad_version/__init__.py
triad-0.9.8.dist-info/LICENSE
triad-0.9.8.dist-info/METADATA
triad-0.9.8.dist-info/WHEEL
triad-0.9.8.dist-info/top_level.txt
triad-0.9.8.dist-info/RECORD
