Metadata-Version: 2.1
Name: triad
Version: 0.9.8
Summary: A collection of python utils for Fugue projects
Home-page: http://github.com/fugue-project/triad
Author: The Fugue Development Team
Author-email: hello@fugue.ai
License: Apache-2.0
Keywords: fugue utilities
Classifier: Development Status :: 5 - Production/Stable
Classifier: Intended Audience :: Developers
Classifier: Topic :: Software Development :: Libraries :: Python Modules
Classifier: License :: OSI Approved :: Apache Software License
Classifier: Programming Language :: Python :: 3.8
Classifier: Programming Language :: Python :: 3.9
Classifier: Programming Language :: Python :: 3.10
Classifier: Programming Language :: Python :: 3.11
Classifier: Programming Language :: Python :: 3.12
Classifier: Programming Language :: Python :: 3 :: Only
Requires-Python: >=3.8
Provides-Extra: ciso8601
License-File: LICENSE
